wskbb/__init__.py
wskbb/__main__.py
wskbb/utils.py
wskbb/wskbb.py
wskbb-0.1.0.data/scripts/wskbb
wskbb-0.1.0.dist-info/LICENSE
wskbb-0.1.0.dist-info/METADATA
wskbb-0.1.0.dist-info/WHEEL
wskbb-0.1.0.dist-info/entry_points.txt
wskbb-0.1.0.dist-info/top_level.txt
wskbb-0.1.0.dist-info/RECORD
