Metadata-Version: 2.1
Name: wskbb
Version: 0.1.0
Summary: Command line untuk mengubah image menjadi ala karya Papin dan Agung Botol
Home-page: https://lantip.xyz
Author: Lantip
Author-email: lantip@gmail.com
License-File: LICENSE
Requires-Dist: opencv-python (==4.6.0.66)
Requires-Dist: scikit-image (==0.19.3)
Requires-Dist: matplotlib (==3.5.2)
Requires-Dist: scikit-learn (==1.1.1)
